agent_polis/__init__.py
agent_polis/config.py
agent_polis/main.py
agent_polis/mcp_server.py
agent_polis/sdk.py
agent_polis/a2a/__init__.py
agent_polis/a2a/models.py
agent_polis/a2a/router.py
agent_polis/a2a/task_store.py
agent_polis/actions/__init__.py
agent_polis/actions/analyzer.py
agent_polis/actions/db_models.py
agent_polis/actions/diff.py
agent_polis/actions/models.py
agent_polis/actions/router.py
agent_polis/actions/service.py
agent_polis/agents/__init__.py
agent_polis/agents/db_models.py
agent_polis/agents/models.py
agent_polis/agents/router.py
agent_polis/agents/service.py
agent_polis/events/__init__.py
agent_polis/events/bus.py
agent_polis/events/models.py
agent_polis/events/projections.py
agent_polis/events/store.py
agent_polis/events/types.py
agent_polis/governance/__init__.py
agent_polis/integrations/__init__.py
agent_polis/integrations/crewai.py
agent_polis/shared/__init__.py
agent_polis/shared/db.py
agent_polis/shared/logging.py
agent_polis/shared/middleware.py
agent_polis/shared/redis.py
agent_polis/shared/security.py
agent_polis/simulations/__init__.py
agent_polis/simulations/db_models.py
agent_polis/simulations/models.py
agent_polis/simulations/router.py
agent_polis/simulations/sandbox.py
agent_polis/simulations/service.py
agent_polis/ui/__init__.py
agent_polis/ui/app.py
impact_preview-0.2.1.dist-info/METADATA
impact_preview-0.2.1.dist-info/WHEEL
impact_preview-0.2.1.dist-info/entry_points.txt
impact_preview-0.2.1.dist-info/licenses/LICENSE
impact_preview-0.2.1.dist-info/RECORD
