Metadata-Version: 2.4
Name: impact-preview
Version: 0.2.1
Summary: Impact preview for AI agents - see exactly what will change before any autonomous AI action executes
Project-URL: Homepage, https://github.com/agent-polis/Leviathan
Project-URL: Documentation, https://github.com/agent-polis/Leviathan#readme
Project-URL: Repository, https://github.com/agent-polis/Leviathan
Author: Agent Polis Contributors
License: MIT
License-File: LICENSE
Keywords: agents,ai,approval-workflow,autonomous-agents,impact-preview,safety
Classifier: Development Status :: 3 - Alpha
Classifier: Intended Audience :: Developers
Classifier: License :: OSI Approved :: MIT License
Classifier: Programming Language :: Python :: 3
Classifier: Programming Language :: Python :: 3.11
Classifier: Programming Language :: Python :: 3.12
Classifier: Topic :: Scientific/Engineering :: Artificial Intelligence
Requires-Python: >=3.11
Requires-Dist: alembic>=1.13.0
Requires-Dist: asyncpg>=0.29.0
Requires-Dist: e2b>=0.17.0
Requires-Dist: fastapi>=0.109.0
Requires-Dist: httpx>=0.26.0
Requires-Dist: mcp>=1.0.0
Requires-Dist: passlib[bcrypt]>=1.7.4
Requires-Dist: pydantic-settings>=2.1.0
Requires-Dist: pydantic>=2.5.0
Requires-Dist: python-jose[cryptography]>=3.3.0
Requires-Dist: python-multipart>=0.0.6
Requires-Dist: redis>=5.0.0
Requires-Dist: sqlalchemy[asyncio]>=2.0.25
Requires-Dist: structlog>=24.1.0
Requires-Dist: tenacity>=8.2.0
Requires-Dist: uvicorn[standard]>=0.27.0
Provides-Extra: crewai
Requires-Dist: crewai>=0.22.0; extra == 'crewai'
Provides-Extra: dev
Requires-Dist: aiosqlite>=0.19.0; extra == 'dev'
Requires-Dist: httpx>=0.26.0; extra == 'dev'
Requires-Dist: mypy>=1.8.0; extra == 'dev'
Requires-Dist: pre-commit>=3.6.0; extra == 'dev'
Requires-Dist: pytest-asyncio>=0.23.0; extra == 'dev'
Requires-Dist: pytest-cov>=4.1.0; extra == 'dev'
Requires-Dist: pytest>=7.4.0; extra == 'dev'
Requires-Dist: ruff>=0.1.0; extra == 'dev'
Provides-Extra: ui
Requires-Dist: plotly>=5.18.0; extra == 'ui'
Requires-Dist: streamlit>=1.30.0; extra == 'ui'
